{
  "name": "staging",
  "relativePath": "/staging",
  "responses": [
    {
      "relativepath": "/test",
      "method": "get",
      "responseData": {
        "statusCode": 200,
        "body": "This is get response for [get] Staging /test",
        "headers": ""
      }
    },
    {
      "relativepath": "/test2",
      "method": "get",
      "responseData": {
        "statusCode": 200,
        "body": "This is get response for [get] Staging /test2",
        "headers": ""
      }
    }
  ]
}
